emr_launcher_artifactory/__init__.py
emr_launcher_artifactory-1.0.0.dist-info/DESCRIPTION.rst
emr_launcher_artifactory-1.0.0.dist-info/METADATA
emr_launcher_artifactory-1.0.0.dist-info/RECORD
emr_launcher_artifactory-1.0.0.dist-info/WHEEL
emr_launcher_artifactory-1.0.0.dist-info/metadata.json
emr_launcher_artifactory-1.0.0.dist-info/top_level.txt
