Metadata-Version: 2.0
Name: emr-launcher-artifactory
Version: 1.0.0
Summary: Artifactory plugin providing template functions for emr_launcher
Home-page: https://github.com/tuneinc/emr_launcher_artifactory
Author: Nick Rushton
Author-email: nick@tune.com
License: MIT
Platform: UNKNOWN
Classifier: License :: OSI Approved :: MIT License
Classifier: Programming Language :: Python
Classifier: Programming Language :: Python :: 2.7
Classifier: Programming Language :: Python :: 3
Classifier: Programming Language :: Python :: 3.6
Classifier: Programming Language :: Python :: Implementation :: CPython
Classifier: Programming Language :: Python :: Implementation :: PyPy
Requires-Python: >=2.7.0
Requires-Dist: artifactory (==0.1.17)
Requires-Dist: requests (==2.18.4)
